jitsi_plus_plugin/__init__.py
jitsi_plus_plugin/cli.py
jitsi_plus_plugin/config.py
jitsi_plus_plugin/version.py
jitsi_plus_plugin/core/__init__.py
jitsi_plus_plugin/core/jitsi_connector.py
jitsi_plus_plugin/core/media_server.py
jitsi_plus_plugin/core/signaling.py
jitsi_plus_plugin/features/__init__.py
jitsi_plus_plugin/features/audio_call.py
jitsi_plus_plugin/features/broadcast.py
jitsi_plus_plugin/features/polls.py
jitsi_plus_plugin/features/video_call.py
jitsi_plus_plugin/features/vod.py
jitsi_plus_plugin/features/whiteboard.py
jitsi_plus_plugin/utils/__init__.py
jitsi_plus_plugin/utils/permission.py
jitsi_plus_plugin/utils/scaling.py
tests/__init__.py
tests/test_broadcast_controller.py
tests/test_jitsi_connector.py
tests/test_jitsi_plus_plugin.py
tests/test_media_server_stop_recording_fixed.py
tests/test_media_server_vod.py
tests/test_poll_controller.py
tests/test_signaling.py
tests/test_video_call_controller.py
tests/test_whiteboard_controller_fixed.py
jitsi_plus_plugin-4.2.0.dist-info/METADATA
jitsi_plus_plugin-4.2.0.dist-info/WHEEL
jitsi_plus_plugin-4.2.0.dist-info/entry_points.txt
jitsi_plus_plugin-4.2.0.dist-info/top_level.txt
jitsi_plus_plugin-4.2.0.dist-info/RECORD
