Metadata-Version: 2.4
Name: jitsi-plus-plugin
Version: 4.2.0
Summary: Comprehensive Python integration for Jitsi Meet with video conferencing, audio calls, broadcasting, and VOD
Home-page: https://github.com/Kabhishek18/jitsi-plus-plugin
Author: Kumar Abhishek
Author-email: developer@kabhishek18.com
Project-URL: Documentation, https://github.com/Kabhishek18/jitsi-plus-plugin/docs
Project-URL: Source, https://github.com/Kabhishek18/jitsi-plus-plugin
Project-URL: Tracker, https://github.com/Kabhishek18/jitsi-plus-plugin/issues
Keywords: jitsi,video conference,webrtc,meetings,video chat,real-time communication,broadcasting,vod,audio calls,whiteboard,polls
Classifier: Development Status :: 4 - Beta
Classifier: Intended Audience :: Developers
Classifier: License :: OSI Approved :: MIT License
Classifier: Programming Language :: Python :: 3
Classifier: Programming Language :: Python :: 3.8
Classifier: Programming Language :: Python :: 3.9
Classifier: Programming Language :: Python :: 3.10
Classifier: Programming Language :: Python :: 3.11
Classifier: Topic :: Communications :: Conferencing
Classifier: Topic :: Multimedia :: Video
Classifier: Topic :: Multimedia :: Sound/Audio
Classifier: Topic :: Multimedia :: Video :: Capture
Classifier: Topic :: Multimedia :: Video :: Conversion
Classifier: Topic :: Internet :: WWW/HTTP :: HTTP Servers
Classifier: Topic :: Software Development :: Libraries :: Python Modules
Classifier: Operating System :: OS Independent
Classifier: Framework :: Django
Classifier: Framework :: Flask
Classifier: Framework :: AsyncIO
Requires-Python: >=3.8
Requires-Dist: requests>=2.25.0
Requires-Dist: pyjwt>=2.0.0
Requires-Dist: websockets>=10.0
Requires-Dist: websocket-client>=1.0.0
Requires-Dist: pyyaml>=6.0
Requires-Dist: aiohttp>=3.7.4
Requires-Dist: asyncio>=3.4.3
Requires-Dist: jinja2>=3.0.1
Provides-Extra: django
Requires-Dist: django>=4.0.0; extra == "django"
Provides-Extra: fastapi
Requires-Dist: fastapi>=0.70.0; extra == "fastapi"
Requires-Dist: uvicorn>=0.15.0; extra == "fastapi"
Provides-Extra: flask
Requires-Dist: flask>=2.0.1; extra == "flask"
Provides-Extra: media
Requires-Dist: ffmpeg-python>=0.2.0; extra == "media"
Requires-Dist: av>=8.0.0; extra == "media"
Requires-Dist: m3u8>=0.9.0; extra == "media"
Provides-Extra: aws
Requires-Dist: boto3>=1.17.0; extra == "aws"
Provides-Extra: gcp
Requires-Dist: google-cloud-storage>=2.0.0; extra == "gcp"
Provides-Extra: ai
Requires-Dist: openai>=0.27.0; extra == "ai"
Requires-Dist: whisper-timestamped>=1.0.0; extra == "ai"
Requires-Dist: langchain>=0.0.139; extra == "ai"
Provides-Extra: scaling
Requires-Dist: redis>=4.0.0; extra == "scaling"
Requires-Dist: celery>=5.2.0; extra == "scaling"
Requires-Dist: kubernetes>=24.2.0; extra == "scaling"
Provides-Extra: dev
Requires-Dist: pytest>=6.0.0; extra == "dev"
Requires-Dist: pytest-cov>=2.12.0; extra == "dev"
Requires-Dist: pytest-mock>=3.6.0; extra == "dev"
Requires-Dist: pytest-asyncio>=0.18.0; extra == "dev"
Requires-Dist: requests-mock>=1.9.0; extra == "dev"
Requires-Dist: black>=21.5b2; extra == "dev"
Requires-Dist: flake8>=3.9.0; extra == "dev"
Requires-Dist: mypy>=0.812; extra == "dev"
Requires-Dist: pre-commit>=2.17.0; extra == "dev"
Requires-Dist: twine>=4.0.0; extra == "dev"
Requires-Dist: build>=0.10.0; extra == "dev"
Provides-Extra: docs
Requires-Dist: sphinx>=4.0.0; extra == "docs"
Requires-Dist: sphinx-rtd-theme>=0.5.0; extra == "docs"
Requires-Dist: sphinx-autoapi>=1.8.0; extra == "docs"
Requires-Dist: sphinx-markdown-tables>=0.0.15; extra == "docs"
Provides-Extra: all
Requires-Dist: django>=4.0.0; extra == "all"
Requires-Dist: fastapi>=0.70.0; extra == "all"
Requires-Dist: uvicorn>=0.15.0; extra == "all"
Requires-Dist: flask>=2.0.1; extra == "all"
Requires-Dist: ffmpeg-python>=0.2.0; extra == "all"
Requires-Dist: av>=8.0.0; extra == "all"
Requires-Dist: m3u8>=0.9.0; extra == "all"
Requires-Dist: boto3>=1.17.0; extra == "all"
Requires-Dist: google-cloud-storage>=2.0.0; extra == "all"
Requires-Dist: openai>=0.27.0; extra == "all"
Requires-Dist: whisper-timestamped>=1.0.0; extra == "all"
Requires-Dist: langchain>=0.0.139; extra == "all"
Requires-Dist: redis>=4.0.0; extra == "all"
Requires-Dist: celery>=5.2.0; extra == "all"
Requires-Dist: kubernetes>=24.2.0; extra == "all"
Dynamic: author
Dynamic: author-email
Dynamic: classifier
Dynamic: description
Dynamic: description-content-type
Dynamic: home-page
Dynamic: keywords
Dynamic: project-url
Dynamic: provides-extra
Dynamic: requires-dist
Dynamic: requires-python
Dynamic: summary
